{
  "nepali_date": "Tuesday, 08 Baishakh 2083",
  "english_date": "Tuesday, 21 April 2026",
  "update_timestamp": "2026-04-21T01:19:22.066963+05:45",
  "formatted_display": "English: Tuesday, 21 April 2026 | Nepali: Tuesday, 08 Baishakh 2083",
  "short_english": "21 Apr 2026",
  "short_nepali": "08 Bai 2083",
  "weekday_english": "Tuesday",
  "weekday_nepali": "Tuesday",
  "quote": "To create more positive results in your life, replace 'if only' with 'next time'.",
  "quote_author": "Celestine Chua",
  "formatted_quote": "\"To create more positive results in your life, replace 'if only' with 'next time'.\" - Celestine Chua",
  "quote_status": "success",
  "has_quote_error": false
}