{
  "nepali_date": "Friday, 18 Baishakh 2083",
  "english_date": "Friday, 01 May 2026",
  "update_timestamp": "2026-05-01T01:35:31.436498+05:45",
  "formatted_display": "English: Friday, 01 May 2026 | Nepali: Friday, 18 Baishakh 2083",
  "short_english": "01 May 2026",
  "short_nepali": "18 Bai 2083",
  "weekday_english": "Friday",
  "weekday_nepali": "Friday",
  "quote": "If you do not change direction, you may end up where you are heading.",
  "quote_author": "Lao Tzu",
  "formatted_quote": "\"If you do not change direction, you may end up where you are heading.\" - Lao Tzu",
  "quote_status": "success",
  "has_quote_error": false
}