{
  "nepali_date": "Sunday, 01 Chaitra 2082",
  "english_date": "Sunday, 15 March 2026",
  "update_timestamp": "2026-03-15T00:42:19.307162+05:45",
  "formatted_display": "English: Sunday, 15 March 2026 | Nepali: Sunday, 01 Chaitra 2082",
  "short_english": "15 Mar 2026",
  "short_nepali": "01 Cha 2082",
  "weekday_english": "Sunday",
  "weekday_nepali": "Sunday",
  "quote": "You can't wait for inspiration. You have to go after it with a club. ",
  "quote_author": "Jack London",
  "formatted_quote": "\"You can't wait for inspiration. You have to go after it with a club. \" - Jack London",
  "quote_status": "success",
  "has_quote_error": false
}